[
  {
    "stt": 1,
    "ho_ten": "OLIVER JOHNSON",
    "dong_y": false,
    "khong_dong_y": true,
    "chi_tiet": {
      "ho_ten_ocr": "OLIVER JOHNSON",
      "dong_y_yolo": {
        "co_dau_x": false,
        "so_luong_x_mark": 0,
        "so_luong_x_cancelled": 0,
        "confidence_x_mark": [],
        "confidence_x_cancelled": [],
        "chi_tiet_detection": [],
        "loi": null
      },
      "khong_dong_y_yolo": {
        "co_dau_x": true,
        "so_luong_x_mark": 1,
        "so_luong_x_cancelled": 0,
        "confidence_x_mark": [
          0.8478503227233887
        ],
        "confidence_x_cancelled": [],
        "chi_tiet_detection": [
          {
            "class": "x_mark",
            "confidence": 0.8478503227233887,
            "bbox": [
              254.6433868408203,
              259.5501708984375,
              328.73773193359375,
              358.5423583984375
            ]
          }
        ],
        "loi": null
      },
      "loi": []
    },
    "so_dong": 1
  },
  {
    "stt": 2,
    "ho_ten": "SOPHIA MILER",
    "dong_y": false,
    "khong_dong_y": true,
    "chi_tiet": {
      "ho_ten_ocr": "SOPHIA MILER",
      "dong_y_yolo": {
        "co_dau_x": false,
        "so_luong_x_mark": 0,
        "so_luong_x_cancelled": 0,
        "confidence_x_mark": [],
        "confidence_x_cancelled": [],
        "chi_tiet_detection": [],
        "loi": null
      },
      "khong_dong_y_yolo": {
        "co_dau_x": true,
        "so_luong_x_mark": 1,
        "so_luong_x_cancelled": 0,
        "confidence_x_mark": [
          0.8329573273658752
        ],
        "confidence_x_cancelled": [],
        "chi_tiet_detection": [
          {
            "class": "x_mark",
            "confidence": 0.8329573273658752,
            "bbox": [
              251.74147033691406,
              287.5990905761719,
              325.0535888671875,
              390.3473205566406
            ]
          }
        ],
        "loi": null
      },
      "loi": []
    },
    "so_dong": 2
  },
  {
    "stt": 3,
    "ho_ten": "JAMES ROBINSON",
    "dong_y": true,
    "khong_dong_y": false,
    "chi_tiet": {
      "ho_ten_ocr": "JAMES ROBINSON",
      "dong_y_yolo": {
        "co_dau_x": true,
        "so_luong_x_mark": 1,
        "so_luong_x_cancelled": 0,
        "confidence_x_mark": [
          0.8727028965950012
        ],
        "confidence_x_cancelled": [],
        "chi_tiet_detection": [
          {
            "class": "x_mark",
            "confidence": 0.8727028965950012,
            "bbox": [
              281.8989562988281,
              257.65765380859375,
              365.8250427246094,
              374.93011474609375
            ]
          }
        ],
        "loi": null
      },
      "khong_dong_y_yolo": {
        "co_dau_x": false,
        "so_luong_x_mark": 0,
        "so_luong_x_cancelled": 0,
        "confidence_x_mark": [],
        "confidence_x_cancelled": [],
        "chi_tiet_detection": [],
        "loi": null
      },
      "loi": []
    },
    "so_dong": 3
  },
  {
    "stt": 4,
    "ho_ten": "EMILY HARRIS",
    "dong_y": true,
    "khong_dong_y": false,
    "chi_tiet": {
      "ho_ten_ocr": "EMILY HARRIS",
      "dong_y_yolo": {
        "co_dau_x": true,
        "so_luong_x_mark": 1,
        "so_luong_x_cancelled": 0,
        "confidence_x_mark": [
          0.8570664525032043
        ],
        "confidence_x_cancelled": [],
        "chi_tiet_detection": [
          {
            "class": "x_mark",
            "confidence": 0.8570664525032043,
            "bbox": [
              276.82586669921875,
              257.2457275390625,
              358.94110107421875,
              342.69189453125
            ]
          }
        ],
        "loi": null
      },
      "khong_dong_y_yolo": {
        "co_dau_x": false,
        "so_luong_x_mark": 0,
        "so_luong_x_cancelled": 0,
        "confidence_x_mark": [],
        "confidence_x_cancelled": [],
        "chi_tiet_detection": [],
        "loi": null
      },
      "loi": []
    },
    "so_dong": 4
  },
  {
    "stt": 5,
    "ho_ten": "BENJANIN SCOTT",
    "dong_y": true,
    "khong_dong_y": false,
    "chi_tiet": {
      "ho_ten_ocr": "BENJANIN SCOTT",
      "dong_y_yolo": {
        "co_dau_x": true,
        "so_luong_x_mark": 1,
        "so_luong_x_cancelled": 0,
        "confidence_x_mark": [
          0.8805136680603027
        ],
        "confidence_x_cancelled": [],
        "chi_tiet_detection": [
          {
            "class": "x_mark",
            "confidence": 0.8805136680603027,
            "bbox": [
              276.7469482421875,
              260.2945556640625,
              364.07440185546875,
              393.166015625
            ]
          }
        ],
        "loi": null
      },
      "khong_dong_y_yolo": {
        "co_dau_x": false,
        "so_luong_x_mark": 0,
        "so_luong_x_cancelled": 0,
        "confidence_x_mark": [],
        "confidence_x_cancelled": [],
        "chi_tiet_detection": [],
        "loi": null
      },
      "loi": []
    },
    "so_dong": 5
  },
  {
    "stt": 6,
    "ho_ten": "CHARLOTTE WALKER",
    "dong_y": true,
    "khong_dong_y": false,
    "chi_tiet": {
      "ho_ten_ocr": "CHARLOTTE WALKER",
      "dong_y_yolo": {
        "co_dau_x": true,
        "so_luong_x_mark": 1,
        "so_luong_x_cancelled": 0,
        "confidence_x_mark": [
          0.8662850260734558
        ],
        "confidence_x_cancelled": [],
        "chi_tiet_detection": [
          {
            "class": "x_mark",
            "confidence": 0.8662850260734558,
            "bbox": [
              270.4976806640625,
              253.31512451171875,
              354.08819580078125,
              353.0604248046875
            ]
          }
        ],
        "loi": null
      },
      "khong_dong_y_yolo": {
        "co_dau_x": false,
        "so_luong_x_mark": 0,
        "so_luong_x_cancelled": 0,
        "confidence_x_mark": [],
        "confidence_x_cancelled": [],
        "chi_tiet_detection": [],
        "loi": null
      },
      "loi": []
    },
    "so_dong": 6
  },
  {
    "stt": 7,
    "ho_ten": "WILLIAM TUMER",
    "dong_y": false,
    "khong_dong_y": true,
    "chi_tiet": {
      "ho_ten_ocr": "WILLIAM TUMER",
      "dong_y_yolo": {
        "co_dau_x": false,
        "so_luong_x_mark": 0,
        "so_luong_x_cancelled": 0,
        "confidence_x_mark": [],
        "confidence_x_cancelled": [],
        "chi_tiet_detection": [],
        "loi": null
      },
      "khong_dong_y_yolo": {
        "co_dau_x": true,
        "so_luong_x_mark": 1,
        "so_luong_x_cancelled": 0,
        "confidence_x_mark": [
          0.8997954726219177
        ],
        "confidence_x_cancelled": [],
        "chi_tiet_detection": [
          {
            "class": "x_mark",
            "confidence": 0.8997954726219177,
            "bbox": [
              233.15396118164062,
              288.6236572265625,
              323.0409851074219,
              385.9794921875
            ]
          }
        ],
        "loi": null
      },
      "loi": []
    },
    "so_dong": 7
  },
  {
    "stt": 8,
    "ho_ten": "AMELIA COOPER",
    "dong_y": false,
    "khong_dong_y": true,
    "chi_tiet": {
      "ho_ten_ocr": "AMELIA COOPER",
      "dong_y_yolo": {
        "co_dau_x": false,
        "so_luong_x_mark": 0,
        "so_luong_x_cancelled": 0,
        "confidence_x_mark": [],
        "confidence_x_cancelled": [],
        "chi_tiet_detection": [],
        "loi": null
      },
      "khong_dong_y_yolo": {
        "co_dau_x": true,
        "so_luong_x_mark": 1,
        "so_luong_x_cancelled": 0,
        "confidence_x_mark": [
          0.8717137575149536
        ],
        "confidence_x_cancelled": [],
        "chi_tiet_detection": [
          {
            "class": "x_mark",
            "confidence": 0.8717137575149536,
            "bbox": [
              242.72085571289062,
              296.58453369140625,
              333.3429260253906,
              395.37908935546875
            ]
          }
        ],
        "loi": null
      },
      "loi": []
    },
    "so_dong": 8
  },
  {
    "stt": 9,
    "ho_ten": "DANEL PARKER",
    "dong_y": true,
    "khong_dong_y": false,
    "chi_tiet": {
      "ho_ten_ocr": "DANEL PARKER",
      "dong_y_yolo": {
        "co_dau_x": true,
        "so_luong_x_mark": 1,
        "so_luong_x_cancelled": 0,
        "confidence_x_mark": [
          0.8894792199134827
        ],
        "confidence_x_cancelled": [],
        "chi_tiet_detection": [
          {
            "class": "x_mark",
            "confidence": 0.8894792199134827,
            "bbox": [
              235.35836791992188,
              289.40252685546875,
              329.6483459472656,
              386.81304931640625
            ]
          }
        ],
        "loi": null
      },
      "khong_dong_y_yolo": {
        "co_dau_x": false,
        "so_luong_x_mark": 0,
        "so_luong_x_cancelled": 0,
        "confidence_x_mark": [],
        "confidence_x_cancelled": [],
        "chi_tiet_detection": [],
        "loi": null
      },
      "loi": []
    },
    "so_dong": 9
  },
  {
    "stt": 10,
    "ho_ten": "GRACE MITCHELL",
    "dong_y": false,
    "khong_dong_y": true,
    "chi_tiet": {
      "ho_ten_ocr": "GRACE MITCHELL",
      "dong_y_yolo": {
        "co_dau_x": false,
        "so_luong_x_mark": 0,
        "so_luong_x_cancelled": 0,
        "confidence_x_mark": [],
        "confidence_x_cancelled": [],
        "chi_tiet_detection": [],
        "loi": null
      },
      "khong_dong_y_yolo": {
        "co_dau_x": true,
        "so_luong_x_mark": 1,
        "so_luong_x_cancelled": 0,
        "confidence_x_mark": [
          0.8683651685714722
        ],
        "confidence_x_cancelled": [],
        "chi_tiet_detection": [
          {
            "class": "x_mark",
            "confidence": 0.8683651685714722,
            "bbox": [
              247.48268127441406,
              286.68634033203125,
              339.0098876953125,
              369.68572998046875
            ]
          }
        ],
        "loi": null
      },
      "loi": []
    },
    "so_dong": 10
  }
]